pilotis_io/__init__.py
pilotis_io/__version__.py
pilotis_io/directory_structure.py
pilotis_io/exceptions.py
pilotis_io/io.py
pilotis_io/local/__init__.py
pilotis_io/local/local_io_api.py
pilotis_io/local/local_numpy_api.py
pilotis_io/local/local_pandas_api.py
pilotis_io/numpy.py
pilotis_io/pandas.py
pilotis_io/parser.py
pilotis_io/persistence.py
pilotis_io-0.2.0.dist-info/LICENSE
pilotis_io-0.2.0.dist-info/WHEEL
pilotis_io-0.2.0.dist-info/METADATA
pilotis_io-0.2.0.dist-info/RECORD
